HelloWorldWcy-0.1.data/scripts/say_hello.py
myapp/__init__.py
myapp/great.py
HelloWorldWcy-0.1.dist-info/METADATA
HelloWorldWcy-0.1.dist-info/WHEEL
HelloWorldWcy-0.1.dist-info/top_level.txt
HelloWorldWcy-0.1.dist-info/RECORD
